pygeckopb/__init__.py
pygeckopb/msgs_pb2.py
pygeckopb-0.0.1.dist-info/METADATA
pygeckopb-0.0.1.dist-info/WHEEL
pygeckopb-0.0.1.dist-info/top_level.txt
pygeckopb-0.0.1.dist-info/RECORD
